{
  "generator-jhipster": {
    "promptValues": {
      "packageName": "com.merliontechs.test",
      "nativeLanguage": "es"
    },
    "jhipsterVersion": "6.10.1",
    "applicationType": "monolith",
    "baseName": "Test",
    "packageName": "com.merliontechs.test",
    "packageFolder": "com/merliontechs/test",
    "serverPort": "8080",
    "authenticationType": "jwt",
    "cacheProvider": "ehcache",
    "enableHibernateCache": true,
    "websocket": false,
    "databaseType": "sql",
    "devDatabaseType": "postgresql",
    "prodDatabaseType": "postgresql",
    "searchEngine": false,
    "messageBroker": false,
    "serviceDiscoveryType": false,
    "buildTool": "maven",
    "enableSwaggerCodegen": false,
    "jwtSecretKey": "YmI4NDg4NTI3YWIxYzdhMWJkMTRlNGFjZWY3MTI3NDg1YTY1MzhhY2MzYzMxYjI4NGVhMmU0ZGNlN2RlOTE1ZGUxOTUwODg4NDAzZDY2NmMzMzliYzQyODM3ZDc4ZTg4MjU4Mzg1ODZhOWI2OGQwMjg0ZTMzODkyYmQ0NWE3YTE=",
    "embeddableLaunchScript": false,
    "useSass": true,
    "clientPackageManager": "npm",
    "clientFramework": "react",
    "clientTheme": "none",
    "clientThemeVariant": "",
    "creationTimestamp": 1597501430760,
    "testFrameworks": [],
    "jhiPrefix": "jhi",
    "entitySuffix": "",
    "dtoSuffix": "DTO",
    "otherModules": [],
    "enableTranslation": true,
    "nativeLanguage": "es",
    "languages": ["es"],
    "blueprints": []
  }
}
